fastrank-0.8.0.dist-info/METADATA
fastrank-0.8.0.dist-info/WHEEL
fastrank-0.8.0.dist-info/license_files/LICENSE
fastrank/__init__.py
fastrank/clib.py
fastrank/training.py
fastrank/fastrank/__init__.py
fastrank/fastrank/ffi.py
fastrank/fastrank/native.so
fastrank-0.8.0.dist-info/RECORD
