Metadata-Version: 2.1
Name: fastrank
Version: 0.8.0
Requires-Dist: cffi
Requires-Dist: numpy
License-File: LICENSE
Summary: FastRank Learning to Rank Library written in Rust.
Home-Page: https://github.com/jjfiv/fastrank
Author: John Foley <johnf@middlebury.edu>
Author-email: John Foley <johnf@middlebury.edu>
License: MIT
